llmpy/__init__.py
llmpy/llmpy.py
llmpy_lib-0.0.8.dist-info/METADATA
llmpy_lib-0.0.8.dist-info/WHEEL
llmpy_lib-0.0.8.dist-info/licenses/LICENSE.txt
llmpy_lib-0.0.8.dist-info/RECORD
