Metadata-Version: 2.4
Name: llmpy-lib
Version: 0.0.8
Summary: Easily interact with all main LLMs
Project-URL: Homepage, https://github.com/yourusername/llmpy
Project-URL: Issues, https://github.com/yourusername/llmpy/issues
Author-email: Angelo Zangari <angelo.zangari10@gmail.com>
License-Expression: MIT
License-File: LICENSE.txt
Classifier: Operating System :: OS Independent
Classifier: Programming Language :: Python :: 3
Requires-Python: >=3.10
Requires-Dist: anthropic
Requires-Dist: google-genai
Requires-Dist: groq
Requires-Dist: llmpy-models
Requires-Dist: openai
Requires-Dist: python-dotenv
